README.md
setup.py
syndisk/__init__.py
syndisk/simobs.py
syndisk.egg-info/PKG-INFO
syndisk.egg-info/SOURCES.txt
syndisk.egg-info/dependency_links.txt
syndisk.egg-info/requires.txt
syndisk.egg-info/top_level.txt