Metadata-Version: 1.0
Name: syndisk
Version: 0.0.1
Summary: Tools to simulate observations of protoplanetary disks.
Home-page: https://github.com/richteague/syndisk
Author: Richard Teague
Author-email: richard.d.teague@cfa.harvard.edu
License: UNKNOWN
Platform: UNKNOWN
